LICENSE
README.md
setup.cfg
setup.py
Fancy_aggregations/__init__.py
Fancy_aggregations/binary_parser.py
Fancy_aggregations/dissimilarities.py
Fancy_aggregations/implications.py
Fancy_aggregations/integrals.py
Fancy_aggregations/intervals.py
Fancy_aggregations/intervaluate_OWA.py
Fancy_aggregations/intervaluate_moderate_deviations.py
Fancy_aggregations/moderate_deviations.py
Fancy_aggregations/overlaps.py
Fancy_aggregations/owas.py
Fancy_aggregations/penalties.py
Fancy_aggregations/rankings.py
Fancy_aggregations/supervised_MPA.py
Fancy_aggregations/tensor_CCA.py
Fancy_aggregations/tnorms.py
Fancy_aggregations.egg-info/PKG-INFO
Fancy_aggregations.egg-info/SOURCES.txt
Fancy_aggregations.egg-info/dependency_links.txt
Fancy_aggregations.egg-info/requires.txt
Fancy_aggregations.egg-info/top_level.txt