Metadata-Version: 2.1
Name: Fancy-aggregations
Version: 1.5.1
Summary: A collection of aggregations, such as OWAs, Choquet and Sugeno integrals, etc.
Home-page: https://github.com/Fuminides/Fancy_aggregations
Author: Javier Fumanal Idocin
Author-email: javier.fumanal@unavarra.es
License: UNKNOWN
Platform: UNKNOWN
License-File: LICENSE
